osbdo/__init__.py
osbdo/agents.py
osbdo/create_params.py
osbdo/cvx_sol.py
osbdo/problem.py
osbdo/sol_analyse.py
osbdo/utils.py
osbdo-0.0.6.dist-info/LICENSE
osbdo-0.0.6.dist-info/METADATA
osbdo-0.0.6.dist-info/WHEEL
osbdo-0.0.6.dist-info/top_level.txt
osbdo-0.0.6.dist-info/RECORD
