Metadata-Version: 2.1
Name: osbdo
Version: 0.0.6
Summary: Oracle-Structured Bundle Distributed Optimization
Home-page: https://github.com/cvxgrp/osbdo
License: GPLv3
Platform: UNKNOWN
Classifier: Programming Language :: Python :: 3
Requires-Python: >=3.8
Requires-Dist: cvxpy (>=1.2.0)
Requires-Dist: matplotlib (>=1.16.0)
Requires-Dist: numpy (>=1.22.2)
Requires-Dist: scipy (>=1.8.0)
